docksuitex/__init__.py
docksuitex/autodock4.py
docksuitex/batch_autodock4.py
docksuitex/batch_vina.py
docksuitex/ligand.py
docksuitex/pocket_finder.py
docksuitex/protein.py
docksuitex/vina.py
docksuitex/utils/__init__.py
docksuitex/utils/cleaner.py
docksuitex/utils/fetcher.py
docksuitex/utils/parser.py
docksuitex/utils/viewer.py
docksuitex-2.0.2.dist-info/licenses/LICENSE
examples/multiple_ligand_docking.ipynb
examples/single_ligand_docking.ipynb
docksuitex-2.0.2.dist-info/METADATA
docksuitex-2.0.2.dist-info/WHEEL
docksuitex-2.0.2.dist-info/top_level.txt
docksuitex-2.0.2.dist-info/RECORD
