Metadata-Version: 2.4
Name: DockSuiteX
Version: 2.0.2
Summary: All-in-one protein-ligand docking package for Windows with bundled tools
Author-email: Mangalam Gautam Sinha <mangalamgsinha@gmail.com>
License:                     GNU GENERAL PUBLIC LICENSE
Project-URL: Homepage, https://github.com/MangalamGSinha/DockSuiteX
Project-URL: Documentation, https://github.com/MangalamGSinha/DockSuiteX/wiki
Project-URL: Source, https://github.com/MangalamGSinha/DockSuiteX
Project-URL: Issue Tracker, https://github.com/MangalamGSinha/DockSuiteX/issues
Keywords: docking,autodock,vina,bioinformatics,ligand,protein,drug discovery
Classifier: Development Status :: 4 - Beta
Classifier: Intended Audience :: Science/Research
Classifier: License :: OSI Approved :: GNU General Public License v3 (GPLv3)
Classifier: Operating System :: Microsoft :: Windows
Classifier: Programming Language :: Python :: 3
Classifier: Topic :: Scientific/Engineering :: Bio-Informatics
Requires-Python: >=3.9
License-File: LICENSE
Requires-Dist: pdbfixer-wheel>=1.11.0
Requires-Dist: OpenMM>=8.3.1
Requires-Dist: pandas>=1.3
Requires-Dist: requests>=2.26
Requires-Dist: nglview
Requires-Dist: ipywidgets
Dynamic: license-file
